kloudio/__init__.py
kloudio/api_client.py
kloudio/configuration.py
kloudio/exceptions.py
kloudio/rest.py
kloudio/api/__init__.py
kloudio/api/connections_api.py
kloudio/api/jobs_api.py
kloudio/api/license_api.py
kloudio/api/register_api.py
kloudio/api/reports_api.py
kloudio/models/__init__.py
kloudio/models/connection_del_response.py
kloudio/models/connection_respose.py
kloudio/models/connection_share_response.py
kloudio/models/error_response.py
kloudio/models/jobs_array.py
kloudio/models/new_connection.py
kloudio/models/new_job.py
kloudio/models/new_license.py
kloudio/models/new_report.py
kloudio/models/new_user.py
kloudio/models/report_del_response.py
kloudio/models/report_share_response.py
kloudio/models/reports_response.py
kloudio/models/run_report.py
kloudio/models/share_connection.py
kloudio/models/share_report.py
kloudio/models/update_connection.py
kloudio/models/update_license.py
Kloudio-1.0.0.dist-info/METADATA
Kloudio-1.0.0.dist-info/WHEEL
Kloudio-1.0.0.dist-info/top_level.txt
Kloudio-1.0.0.dist-info/RECORD
