Metadata-Version: 2.1
Name: Kloudio
Version: 1.0.0
Summary: Kloudio APIs
Home-page: https://github.com/Kloudio/sdk-python
Author: Kloudio
Author-email: developer@kloud.io
License: UNKNOWN
Keywords: SDK,API,Kloudio APIs
Platform: UNKNOWN
Requires-Dist: certifi
Requires-Dist: python-dateutil
Requires-Dist: six (>=1.10)
Requires-Dist: urllib3 (>=1.15)
